calculator_01/__init__.py
calculator_01/calculator_main.py
calculator_01/calculator_session.py
calculator_01-1.0.0.dist-info/LICENSE.txt
calculator_01-1.0.0.dist-info/METADATA
calculator_01-1.0.0.dist-info/WHEEL
calculator_01-1.0.0.dist-info/top_level.txt
calculator_01-1.0.0.dist-info/RECORD
