Metadata-Version: 2.1
Name: calculator-01
Version: 1.0.0
Summary: A simple Python calculator
Author: Gabija Gedvilaite
Author-email: gabija_g@hotmail.com
Classifier: Programming Language :: Python :: 3
Classifier: License :: OSI Approved :: MIT License
Classifier: Operating System :: OS Independent
Requires-Python: >=3.7
License-File: LICENSE.txt
